shit/__init__.py
shit/game.py
shit/web/static/index.html
shit/web/static/css/style.css
shit/web/static/images/toilet.jpg
shit/web/static/images/toilet1.jpg
shit/web/static/js/game.js
shitventure-1.0.0.1.dist-info/licenses/LICENSE
shitventure-1.0.0.1.dist-info/METADATA
shitventure-1.0.0.1.dist-info/WHEEL
shitventure-1.0.0.1.dist-info/entry_points.txt
shitventure-1.0.0.1.dist-info/top_level.txt
shitventure-1.0.0.1.dist-info/RECORD
